dj_wallet/__init__.py
dj_wallet/abstract_models.py
dj_wallet/admin.py
dj_wallet/apps.py
dj_wallet/conf.py
dj_wallet/exceptions.py
dj_wallet/managers.py
dj_wallet/migrations/0001_initial.py
dj_wallet/migrations/__init__.py
dj_wallet/mixins.py
dj_wallet/models.py
dj_wallet/services/__init__.py
dj_wallet/services/common.py
dj_wallet/services/exchange.py
dj_wallet/services/purchase.py
dj_wallet/services/transfer.py
dj_wallet/signals.py
dj_wallet/utils.py
dj_wallet-0.1.0.dist-info/LICENSE
dj_wallet-0.1.0.dist-info/METADATA
dj_wallet-0.1.0.dist-info/WHEEL
dj_wallet-0.1.0.dist-info/RECORD
