Metadata-Version: 2.3
Name: dj-wallet
Version: 0.1.0
Summary: A secure, flexible virtual wallet system for Django applications
License: MIT
Keywords: django,wallet,payments,transactions,virtual-currency,fintech
Author: Khaled Sukkar
Author-email: khaled.sukkar.contact@gmail.com
Requires-Python: >=3.9,<4.0
Classifier: Development Status :: 4 - Beta
Classifier: Environment :: Web Environment
Classifier: Framework :: Django
Classifier: Framework :: Django :: 3.2
Classifier: Framework :: Django :: 4.0
Classifier: Framework :: Django :: 4.1
Classifier: Framework :: Django :: 4.2
Classifier: Framework :: Django :: 5.0
Classifier: Intended Audience :: Developers
Classifier: License :: OSI Approved :: MIT License
Classifier: Operating System :: OS Independent
Classifier: Programming Language :: Python
Classifier: Programming Language :: Python :: 3
Classifier: Programming Language :: Python :: 3.9
Classifier: Programming Language :: Python :: 3.10
Classifier: Programming Language :: Python :: 3.11
Classifier: Programming Language :: Python :: 3.12
Classifier: Programming Language :: Python :: 3.13
Classifier: Topic :: Internet :: WWW/HTTP
Classifier: Topic :: Software Development :: Libraries :: Python Modules
Provides-Extra: drf
Requires-Dist: django (>=3.2)
Requires-Dist: djangorestframework (>=3.12) ; extra == "drf"
Project-URL: Changelog, https://github.com/khaledsukkar2/dj-wallet/blob/main/CHANGELOG.md
Project-URL: Documentation, https://github.com/khaledsukkar2/dj-wallet#readme
Project-URL: Homepage, https://github.com/khaledsukkar2/dj-wallet
Project-URL: Issues, https://github.com/khaledsukkar2/dj-wallet/issues
Project-URL: Repository, https://github.com/khaledsukkar2/dj-wallet.git
